types_alya/__init__.py
types_alya/api_wrapper.py
types_alya/objects.py
types_alya-8.3.1.dist-info/METADATA
types_alya-8.3.1.dist-info/WHEEL
types_alya-8.3.1.dist-info/top_level.txt
types_alya-8.3.1.dist-info/RECORD
