Metadata-Version: 2.4
Name: types-alya
Version: 8.3.1
Summary: Autogenerated wrapper for telegram api.
Requires-Python: >=3.9
Requires-Dist: httpx>=0.28.1
Requires-Dist: pydantic>=2.11.5
